langacore
