Metadata-Version: 1.0
Name: langacore.kit.i18n
Version: 0.1.6
Summary: Various common i18n-related routines.
Home-page: UNKNOWN
Author: LangaCore, Lukasz Langa, Krzysztof Borowczyk
Author-email: support@langacore.org, lukasz@langa.pl, krzysztof@bordev.pl
License: GPL v3
Platform: any
Classifier: Development Status :: 3 - Alpha
Classifier: Intended Audience :: Developers
Classifier: License :: OSI Approved :: GNU General Public License (GPL)
Classifier: Natural Language :: English
Classifier: Programming Language :: Python
Classifier: Programming Language :: Python :: 2.7
Classifier: Topic :: Software Development :: Libraries :: Python Modules
